django_ga_measurement_protocol/__init__.py
django_ga_measurement_protocol/middleware.py
django_ga_measurement_protocol/track.py
django_ga_measurement_protocol/tests/__init__.py
django_ga_measurement_protocol/tests/settings.py
django_ga_measurement_protocol/tests/test_middleware.py
django_ga_measurement_protocol/tests/test_tracking.py
django_ga_measurement_protocol/tests/urls.py
django_ga_measurement_protocol/tests/testapp/__init__.py
django_ga_measurement_protocol/tests/testapp/urls.py
django_ga_measurement_protocol/tests/testapp/views.py
django_ga_measurement_protocol-0.2.0.dist-info/LICENSE
django_ga_measurement_protocol-0.2.0.dist-info/METADATA
django_ga_measurement_protocol-0.2.0.dist-info/WHEEL
django_ga_measurement_protocol-0.2.0.dist-info/top_level.txt
django_ga_measurement_protocol-0.2.0.dist-info/RECORD
